Metadata-Version: 1.2
Name: calligra
Version: 0.3
Summary: C language metaprogramming and code generation from Python
Home-page: https://github.com/marmeladema/calligra
Author: Elie ROUDNINSKI
Author-email: xademax@gmail.com
License: MIT
Download-URL: https://github.com/marmeladema/calligra/archive/0.3.tar.gz
Platform: UNKNOWN
Classifier: Development Status :: 3 - Alpha
Classifier: Intended Audience :: Developers
Classifier: Topic :: Software Development :: Code Generators
Classifier: License :: OSI Approved :: MIT License
Classifier: Programming Language :: Python :: 3
Requires-Python: >=3
